drf_registration/__init__.py
drf_registration/admin.py
drf_registration/apps.py
drf_registration/auth.py
drf_registration/constants.py
drf_registration/exceptions.py
drf_registration/settings.py
drf_registration/tokens.py
drf_registration/urls.py
drf_registration/api/__init__.py
drf_registration/api/change_password.py
drf_registration/api/login.py
drf_registration/api/logout.py
drf_registration/api/profile.py
drf_registration/api/register.py
drf_registration/api/reset_password.py
drf_registration/api/set_password.py
drf_registration/api/user.py
drf_registration/utils/__init__.py
drf_registration/utils/common.py
drf_registration/utils/domain.py
drf_registration/utils/email.py
drf_registration/utils/responses.py
drf_registration/utils/socials.py
drf_registration/utils/users.py
drf_registration-0.1.3.dist-info/LICENSE.txt
drf_registration-0.1.3.dist-info/METADATA
drf_registration-0.1.3.dist-info/WHEEL
drf_registration-0.1.3.dist-info/top_level.txt
drf_registration-0.1.3.dist-info/RECORD
