Metadata-Version: 2.1
Name: drf-registration
Version: 0.1.3
Summary: Simple user registration package based on Django Rest Framework. DRF Registration - The easy way to generate registration RESTful APIs.
Home-page: https://github.com/huychau/drf-registration
Author: Huy Chau
Author-email: huychau.dev@gmail.com
License: UNKNOWN
Platform: UNKNOWN
Requires-Python: >=3.6
License-File: LICENSE.txt
